pyfingerd/__init__.py
pyfingerd/__main__.py
pyfingerd/binds.py
pyfingerd/cli.py
pyfingerd/core.py
pyfingerd/errors.py
pyfingerd/fiction.py
pyfingerd/native.py
pyfingerd/posix.py
pyfingerd/server.py
pyfingerd/utils.py
pyfingerd-0.5.1.dist-info/LICENSE.txt
pyfingerd-0.5.1.dist-info/METADATA
pyfingerd-0.5.1.dist-info/WHEEL
pyfingerd-0.5.1.dist-info/entry_points.txt
pyfingerd-0.5.1.dist-info/RECORD
