Metadata-Version: 2.1
Name: pyfingerd
Version: 0.5.1
Summary: finger (RFC 1288) server-side daemon
Home-page: https://pyfingerd.org/
Keywords: finger,fingerd,rfc742,rfc1288,79,tcp/79
Author: Thomas Touhey
Author-email: thomas@touhey.fr
Requires-Python: >=3.11,<4.0
Classifier: Development Status :: 3 - Alpha
Classifier: Intended Audience :: System Administrators
Classifier: License :: OSI Approved :: MIT License
Classifier: Natural Language :: English
Classifier: Programming Language :: Python :: 3
Classifier: Programming Language :: Python :: 3.11
Classifier: Topic :: Internet :: Finger
Classifier: Topic :: Utilities
Requires-Dist: click (>=8.1.6,<9.0.0)
Requires-Dist: coloredlogs (>=15.0.1,<16.0.0)
Requires-Dist: croniter (>=1.4.1,<2.0.0)
Requires-Dist: pydantic (>=2.1.1,<3.0.0)
Requires-Dist: pyutmpx (>=0.4.1,<0.5.0)
Requires-Dist: toml (>=0.10.2,<0.11.0)
Project-URL: Repository, https://gitlab.com/pyfingerd/pyfingerd
